arqworker/__init__.py
arqworker/classes.py
arqworker/client.py
arqworker/config.py
arqworker/construct.py
arqworker/deploy.py
arqworker/utils.py
arq_worker-0.0.0a0.dist-info/METADATA
arq_worker-0.0.0a0.dist-info/WHEEL
arq_worker-0.0.0a0.dist-info/top_level.txt
arq_worker-0.0.0a0.dist-info/RECORD
