Metadata-Version: 2.1
Name: arq-worker
Version: 0.0.0a0
Summary: A high level abstraction designed for running arq in api-driven apps
Home-page: https://github.com/trisongz/arq-worker
Author: trisongz
Author-email: ts@growthengineai.com
License: MIT Style
Platform: UNKNOWN
Classifier: Intended Audience :: Developers
Classifier: License :: OSI Approved :: MIT License
Classifier: Programming Language :: Python :: 3.7
Classifier: Topic :: Software Development :: Libraries
Requires-Python: >=3.7
Requires-Dist: lazycls
Requires-Dist: pylogz
Requires-Dist: arq
Requires-Dist: redis
